grafatko/__init__.py
grafatko/animation.py
grafatko/color.py
grafatko/controls.py
grafatko/graph.py
grafatko/utilities.py
grafatko-0.2.6.data/data/DOCUMENTATION.md
grafatko-0.2.6.data/data/LICENSE.txt
grafatko-0.2.6.data/data/README.md
grafatko-0.2.6.data/data/icon.ico
grafatko-0.2.6.dist-info/LICENSE.txt
grafatko-0.2.6.dist-info/METADATA
grafatko-0.2.6.dist-info/WHEEL
grafatko-0.2.6.dist-info/entry_points.txt
grafatko-0.2.6.dist-info/top_level.txt
grafatko-0.2.6.dist-info/RECORD
