Metadata-Version: 2.1
Name: grafatko
Version: 0.2.6
Summary: An app for creating and visualizing graphs and graph-related algorithms.
Home-page: https://github.com/xiaoxiae/Grafatko
Author: Tomáš Sláma
Author-email: tomas@slama.dev
License: UNKNOWN
Keywords: graph graphs pyqt5 algorithm algorithms
Platform: UNKNOWN
Classifier: Programming Language :: Python :: 3
Classifier: License :: OSI Approved :: MIT License
Classifier: Operating System :: OS Independent
Requires-Python: >=3.7.1
Requires-Dist: pyqt5
Requires-Dist: qtmodern
